anon_lockout/__init__.py
anon_lockout/admin.py
anon_lockout/apps.py
anon_lockout/conf.py
anon_lockout/handlers.py
anon_lockout/models.py
anon_lockout/utils.py
anon_lockout/management/__init__.py
anon_lockout/management/commands/delete_lockout_data.py
anon_lockout/management/commands/invalidate_lockouts.py
anon_lockout/migrations/0001_initial.py
anon_lockout/migrations/0002_accesssession_successes.py
anon_lockout/migrations/__init__.py
django_anon_lockout-2.1.0.dist-info/METADATA
django_anon_lockout-2.1.0.dist-info/WHEEL
django_anon_lockout-2.1.0.dist-info/licenses/LICENSE
django_anon_lockout-2.1.0.dist-info/RECORD
