Metadata-Version: 2.1
Name: django-anon-lockout
Version: 2.1.0
Summary: Django module for anonymous lockout
Project-URL: Homepage, https://github.com/erlendps/django-anon-lockout
Project-URL: Bug Tracker, https://github.com/erlendps/django-anon-lockout/issues
Author-email: Erlend Paulsen Skaaden <erlendskaaden@gmail.com>
License-File: LICENSE
Classifier: License :: OSI Approved :: MIT License
Classifier: Operating System :: OS Independent
Classifier: Programming Language :: Python :: 3
Requires-Python: >=3.7
